README.md
setup.py
django_libreports.egg-info/PKG-INFO
django_libreports.egg-info/SOURCES.txt
django_libreports.egg-info/dependency_links.txt
django_libreports.egg-info/requires.txt
django_libreports.egg-info/top_level.txt
reports/__init__.py
reports/admin.py
reports/base.py
reports/conf.py
reports/models.py
reports/tasks.py
reports/utils.py
reports/migrations/0001_auto_20171002_1641.py
reports/migrations/0001_initial.py
reports/migrations/0002_auto_20171117_1004.py
reports/migrations/0003_auto_20171119_1232.py
reports/migrations/0004_auto_20180502_1350.py
reports/migrations/0005_auto_20190930_1822.py
reports/migrations/__init__.py
reports/runtests/__init__.py
reports/runtests/runtests.py
reports/runtests/settings.py
reports/runtests/example/__init__.py
reports/runtests/example/models.py
reports/runtests/example/my_reports/__init__.py
reports/runtests/example/my_reports/example.py
reports/tests/__init__.py
reports/tests/models_report.py
reports/tests/models_schedule_report.py