Metadata-Version: 1.1
Name: django-libreports
Version: 0.0.17
Summary: Django app to allow creating custom reports easily.
Home-page: http://github.com/AdvancedThreatAnalytics/django-libreport
Author: Advanced Threat Analytics Inc.
Author-email: simon@advancedthreatanalytics.com
License: BSD
Platform: UNKNOWN
Classifier: Development Status :: 4 - Beta
Classifier: Environment :: Web Environment
Classifier: Framework :: Django
Classifier: Intended Audience :: Developers
Classifier: License :: OSI Approved :: BSD License
Classifier: Operating System :: OS Independent
Classifier: Programming Language :: Python
Classifier: Programming Language :: Python :: 3
Classifier: Topic :: Internet :: WWW/HTTP
